MANIFEST.in
README.txt
setup.py
dist/medialog.popupworkflow-0.7.tar.gz
docs/HISTORY.txt
docs/LICENSE.GPL
docs/LICENSE.txt
medialog/.DS_Store
medialog/__init__.py
medialog.popupworkflow.egg-info/PKG-INFO
medialog.popupworkflow.egg-info/SOURCES.txt
medialog.popupworkflow.egg-info/dependency_links.txt
medialog.popupworkflow.egg-info/entry_points.txt
medialog.popupworkflow.egg-info/namespace_packages.txt
medialog.popupworkflow.egg-info/not-zip-safe
medialog.popupworkflow.egg-info/paster_plugins.txt
medialog.popupworkflow.egg-info/requires.txt
medialog.popupworkflow.egg-info/top_level.txt
medialog/popupworkflow/.DS_Store
medialog/popupworkflow/__init__.py
medialog/popupworkflow/configure.zcml
medialog/popupworkflow/tests.py
medialog/popupworkflow/browser/.DS_Store
medialog/popupworkflow/browser/__init__.py
medialog/popupworkflow/browser/configure.zcml
medialog/popupworkflow/browser/view.py
medialog/popupworkflow/profiles/.DS_Store
medialog/popupworkflow/profiles/default/.DS_Store
medialog/popupworkflow/profiles/default/jsregistry.xml
medialog/popupworkflow/profiles/default/metadata.xml
medialog/popupworkflow/profiles/default/skins.xml
medialog/popupworkflow/profiles/default/workflows.xml
medialog/popupworkflow/profiles/default/workflows/.DS_Store
medialog/popupworkflow/profiles/default/workflows/popup_workflow/definition.xml
medialog/popupworkflow/skins/.DS_Store
medialog/popupworkflow/skins/popupworkflow/.DS_Store
medialog/popupworkflow/skins/popupworkflow/placeit.pt