Metadata-Version: 1.0
Name: medialog.popupworkflow
Version: 4.1.5.1
Summary: A workflow for Plone >= 4.1  with a state that opens documents in an overlay
Home-page: https://github.com/espenmn/medialog.popupworkflow
Author: Espen Moe-Nilssen
Author-email: espen@medialog.no
License: GPL
Keywords: plone  workflow  popup
Platform: UNKNOWN
Classifier: Framework :: Plone
Classifier: Programming Language :: Python
